cardano/__init__.py
cardano/wt/__init__.py
cardano/wt/blockfrost.py
cardano/wt/cardano_cli.py
cardano/wt/mint.py
cardano/wt/network.py
cardano/wt/nft_vending_machine.py
cardano/wt/utxo.py
cardano/wt/bonuses/__init__.py
cardano/wt/bonuses/bogo.py
cardano/wt/whitelist/__init__.py
cardano/wt/whitelist/asset_whitelist.py
cardano/wt/whitelist/filesystem.py
cardano/wt/whitelist/no_whitelist.py
cardano/wt/whitelist/wallet_whitelist.py
cardano_nft_vending_machine-0.8.1.dist-info/LICENSE
cardano_nft_vending_machine-0.8.1.dist-info/METADATA
cardano_nft_vending_machine-0.8.1.dist-info/WHEEL
cardano_nft_vending_machine-0.8.1.dist-info/top_level.txt
cardano_nft_vending_machine-0.8.1.dist-info/RECORD
