Metadata-Version: 2.1
Name: cardano-nft-vending-machine
Version: 0.8.1
Summary: Library to perform NFT mints automatically on the Cardano blockchain
Project-URL: Documentation, https://thaddeusdiamond.github.io/cardano-nft-vending-machine/cardano/
Project-URL: Source, https://github.com/thaddeusdiamond/cardano-nft-vending-machine
Classifier: Intended Audience :: Developers
Classifier: License :: OSI Approved :: Apache Software License
Classifier: Natural Language :: English
Classifier: Operating System :: OS Independent
Classifier: Programming Language :: Python :: 3
Requires-Python: >=3.8
License-File: LICENSE
Requires-Dist: Deprecated (>=1.2.13)
Requires-Dist: requests (>=2.27.1)
Requires-Dist: pycardano (>=0.7.2)
